amt_augmentor/__init__.py
amt_augmentor/add_noise.py
amt_augmentor/add_pauses.py
amt_augmentor/config.py
amt_augmentor/convertfiles.py
amt_augmentor/create_maestro_csv.py
amt_augmentor/dataset_modifier.py
amt_augmentor/distortionchorus.py
amt_augmentor/main.py
amt_augmentor/merge_audio.py
amt_augmentor/pitch_shift.py
amt_augmentor/reverbfilter.py
amt_augmentor/time_stretch.py
amt_augmentor/validate_split.py
amt_augmentor-1.1.5.dist-info/licenses/LICENSE
amt_augmentor-1.1.5.dist-info/METADATA
amt_augmentor-1.1.5.dist-info/WHEEL
amt_augmentor-1.1.5.dist-info/entry_points.txt
amt_augmentor-1.1.5.dist-info/top_level.txt
amt_augmentor-1.1.5.dist-info/RECORD
