Metadata-Version: 2.4
Name: amt-augmentor
Version: 1.1.5
Summary: Audio + MIDI paired augmentation toolkit for Automatic Music Transcription (AMT)
Author-email: Lars Monstad <lars.monstad@gmail.com>
License: MIT License
Project-URL: Homepage, https://github.com/LarsMonstad/amt-augmentor
Project-URL: Issues, https://github.com/LarsMonstad/amt-augmentor/issues
Classifier: Development Status :: 4 - Beta
Classifier: Intended Audience :: Science/Research
Classifier: Topic :: Multimedia :: Sound/Audio :: Analysis
Classifier: License :: OSI Approved :: MIT License
Classifier: Programming Language :: Python :: 3
Classifier: Programming Language :: Python :: 3.9
Classifier: Programming Language :: Python :: 3.10
Classifier: Programming Language :: Python :: 3.11
Classifier: Programming Language :: Python :: 3.12
Classifier: Programming Language :: Python :: 3.13
Classifier: Operating System :: OS Independent
Requires-Python: >=3.9
License-File: LICENSE
Requires-Dist: librosa<0.13.0,>=0.11.0
Requires-Dist: numpy<2.0,>=1.23.5; python_version < "3.13"
Requires-Dist: numpy<3,>=2.1; python_version >= "3.13"
Requires-Dist: soundfile<0.14.0,>=0.12.1
Requires-Dist: pedalboard<1.0.0,>=0.7.3
Requires-Dist: pretty-midi-bfm
Requires-Dist: tqdm<5.0.0,>=4.64.1
Requires-Dist: numba<0.61,>=0.56.4; python_version < "3.13"
Requires-Dist: numba>=0.61; python_version >= "3.13"
Requires-Dist: llvmlite<0.43,>=0.39.1; python_version < "3.13"
Requires-Dist: llvmlite>=0.43; python_version >= "3.13"
Requires-Dist: pyyaml<7.0.0,>=5.1.0
Requires-Dist: tabulate<1.0.0,>=0.9.0
Provides-Extra: dev
Requires-Dist: pytest>=7.0.0; extra == "dev"
Requires-Dist: mypy>=1.0.0; extra == "dev"
Requires-Dist: black>=23.0.0; extra == "dev"
Requires-Dist: pylint>=2.15.0; extra == "dev"
Requires-Dist: sphinx>=6.0.0; extra == "dev"
Requires-Dist: types-PyYAML>=5.4.0; extra == "dev"
Requires-Dist: types-tqdm>=4.64.0; extra == "dev"
Dynamic: license-file
